<?xml version="1.0" encoding="utf-8"?>
<odoo>

    <record id="estate_property_type_form_view" model="ir.ui.view">
        <field name="name">estate.property.type.form.view</field>
        <field name="model">estate.property.type</field>
        <field name="arch" type="xml">
            <form string="Property Type">
                <sheet>
                    <h1>House</h1> 
                    <notebook>
                        <page string="Properties">
                            <field name="property_ids">
                                <tree>
                                    <field name="name" string="Title"/>
                                    <field name="expected_price"/>
                                    <field name="state"/>
                                </tree>
                            </field>
                        </page>
                    </notebook>
                </sheet>
            </form>
        </field>
    </record>

</odoo>